mamood_django_admin_log_viewer/__init__.py
mamood_django_admin_log_viewer/admin.py
mamood_django_admin_log_viewer/apps.py
mamood_django_admin_log_viewer/conf.py
mamood_django_admin_log_viewer/defaults.py
mamood_django_admin_log_viewer/middleware.py
mamood_django_admin_log_viewer/models.py
mamood_django_admin_log_viewer/tests.py
mamood_django_admin_log_viewer/urls.py
mamood_django_admin_log_viewer/utils.py
mamood_django_admin_log_viewer/utils_backup.py
mamood_django_admin_log_viewer/views.py
mamood_django_admin_log_viewer/static/mamood_django_admin_log_viewer/css/live_mode.css
mamood_django_admin_log_viewer/static/mamood_django_admin_log_viewer/css/log_viewer.css
mamood_django_admin_log_viewer/static/mamood_django_admin_log_viewer/js/log_viewer.js
mamood_django_admin_log_viewer/templates/mamood_django_admin_log_viewer/log_detail.html
mamood_django_admin_log_viewer/templates/mamood_django_admin_log_viewer/log_list.html
mamood_django_admin_log_viewer/templatetags/__init__.py
mamood_django_admin_log_viewer-2.0.4.dist-info/licenses/LICENSE
mamood_django_admin_log_viewer-2.0.4.dist-info/METADATA
mamood_django_admin_log_viewer-2.0.4.dist-info/WHEEL
mamood_django_admin_log_viewer-2.0.4.dist-info/top_level.txt
mamood_django_admin_log_viewer-2.0.4.dist-info/RECORD
