Metadata-Version: 2.4
Name: mamood-django-admin-log-viewer
Version: 2.0.4
Summary: A Django app for viewing log files in the admin interface
Author-email: Amirhossein Mahmoudi <am.mahmoudi@outlook.com>
License-Expression: MIT
Project-URL: Homepage, https://github.com/ammahmoudi/mamood-django-admin-log-viewer
Project-URL: Documentation, https://github.com/ammahmoudi/mamood-django-admin-log-viewer#readme
Project-URL: Repository, https://github.com/ammahmoudi/mamood-django-admin-log-viewer
Project-URL: Bug Reports, https://github.com/ammahmoudi/mamood-django-admin-log-viewer/issues
Project-URL: Changelog, https://github.com/ammahmoudi/mamood-django-admin-log-viewer/blob/main/CHANGELOG.md
Keywords: django,admin,log,viewer,monitoring,tail,real-time
Classifier: Development Status :: 5 - Production/Stable
Classifier: Intended Audience :: Developers
Classifier: Operating System :: OS Independent
Classifier: Programming Language :: Python :: 3
Classifier: Programming Language :: Python :: 3.8
Classifier: Programming Language :: Python :: 3.9
Classifier: Programming Language :: Python :: 3.10
Classifier: Programming Language :: Python :: 3.11
Classifier: Programming Language :: Python :: 3.12
Classifier: Framework :: Django
Classifier: Framework :: Django :: 4.0
Classifier: Framework :: Django :: 4.1
Classifier: Framework :: Django :: 4.2
Classifier: Framework :: Django :: 5.0
Classifier: Framework :: Django :: 5.1
Classifier: Framework :: Django :: 5.2
Classifier: Topic :: Internet :: WWW/HTTP :: Dynamic Content
Classifier: Topic :: Software Development :: Libraries :: Python Modules
Classifier: Topic :: System :: Logging
Classifier: Topic :: System :: Systems Administration
Requires-Python: >=3.8
License-File: LICENSE
Requires-Dist: Django>=4.2
Provides-Extra: dev
Requires-Dist: pytest; extra == "dev"
Requires-Dist: pytest-django; extra == "dev"
Requires-Dist: pytest-cov; extra == "dev"
Requires-Dist: flake8; extra == "dev"
Requires-Dist: black; extra == "dev"
Dynamic: license-file
